omv/__init__.py
omv/autogen.py
omv/experiment.py
omv/find_tests.py
omv/omt_mep_parser.py
omv/omv_util.py
omv/parse_omt.py
omv/tally.py
omv/analyzers/__init__.py
omv/analyzers/activation.py
omv/analyzers/analyzer.py
omv/analyzers/dryrun.py
omv/analyzers/input_resistance.py
omv/analyzers/morphology.py
omv/analyzers/rates.py
omv/analyzers/resting.py
omv/analyzers/spikes.py
omv/analyzers/temperature.py
omv/analyzers/timeseries.py
omv/analyzers/utils/__init__.py
omv/analyzers/utils/filenode.py
omv/analyzers/utils/timeseries.py
omv/common/__init__.py
omv/common/inout.py
omv/engines/__init__.py
omv/engines/arbor_.py
omv/engines/brian1.py
omv/engines/brian2_.py
omv/engines/eden_.py
omv/engines/engine.py
omv/engines/genesis.py
omv/engines/getarbor.py
omv/engines/getbrian1.py
omv/engines/getbrian2.py
omv/engines/geteden.py
omv/engines/getgenesis.py
omv/engines/getjlems.py
omv/engines/getjnml.py
omv/engines/getlibsbml.py
omv/engines/getmoose.py
omv/engines/getnest.py
omv/engines/getnetpyne.py
omv/engines/getneuroconstruct.py
omv/engines/getnml2.py
omv/engines/getnrn.py
omv/engines/getoctave.py
omv/engines/getpylems.py
omv/engines/getpyneuroml.py
omv/engines/getpynn.py
omv/engines/getxpp.py
omv/engines/jlems.py
omv/engines/jneuroml.py
omv/engines/jneuromlbrian.py
omv/engines/jneuromlbrian2.py
omv/engines/jneuromleden.py
omv/engines/jneuromlmoose.py
omv/engines/jneuromlnetpyne.py
omv/engines/jneuromlnetpyne_np2.py
omv/engines/jneuromlnetpyne_np4.py
omv/engines/jneuromlnrn.py
omv/engines/jneuromlpynnnrn.py
omv/engines/jneuromlvalidate.py
omv/engines/jneuromlvalidatev1.py
omv/engines/jneuromlxpp.py
omv/engines/moose_.py
omv/engines/nestsli.py
omv/engines/netpyne_.py
omv/engines/netpyne__np2.py
omv/engines/netpyne__np4.py
omv/engines/neuron_.py
omv/engines/octave.py
omv/engines/pylems.py
omv/engines/pylemsnml2.py
omv/engines/pynest.py
omv/engines/pyneuroconstruct.py
omv/engines/pyneuroml_.py
omv/engines/pyneuromlvalidatesbml.py
omv/engines/pyneuromlxpp.py
omv/engines/pyneuron.py
osbmodelvalidation-0.3.9.dist-info/licenses/LICENSE.lesser
osbmodelvalidation-0.3.9.dist-info/METADATA
osbmodelvalidation-0.3.9.dist-info/WHEEL
osbmodelvalidation-0.3.9.dist-info/entry_points.txt
osbmodelvalidation-0.3.9.dist-info/top_level.txt
osbmodelvalidation-0.3.9.dist-info/RECORD
