Metadata-Version: 2.4
Name: OSBModelValidation
Version: 0.3.9
Summary: Open Source Brain Model validation
Home-page: https://github.com/OpenSourceBrain/osb-model-validation
Author: Boris Marin, Padraig Gleeson
Author-email: borismarin@gmail.com
License: LGPL-3.0-only
Classifier: Intended Audience :: Science/Research
Classifier: License :: OSI Approved :: GNU Lesser General Public License v3 (LGPLv3)
Classifier: Natural Language :: English
Classifier: Operating System :: OS Independent
Classifier: Programming Language :: Python :: 3.9
Classifier: Programming Language :: Python :: 3.10
Classifier: Programming Language :: Python :: 3.11
Classifier: Programming Language :: Python :: 3.12
Classifier: Programming Language :: Python :: 3.13
Classifier: Topic :: Scientific/Engineering
License-File: LICENSE.lesser
Requires-Dist: PyYAML
Requires-Dist: numpy
Requires-Dist: pyrx
Requires-Dist: pathlib; python_version < "3.4"
Requires-Dist: docopt
Requires-Dist: importlib-metadata; python_version < "3.8"
Dynamic: license-file
